Pagination/__init__.py
Pagination/page.py
Pagintion-1.0.dist-info/METADATA
Pagintion-1.0.dist-info/WHEEL
Pagintion-1.0.dist-info/top_level.txt
Pagintion-1.0.dist-info/RECORD
