Metadata-Version: 2.1
Name: Pagintion
Version: 1.0
Summary: 分页组件
Home-page: UNKNOWN
Author: ZhangJian
Author-email: 15332962628@163.com
License: UNKNOWN
Platform: UNKNOWN
Requires-Python: >=3
Requires-Dist: django
